{
    "10": {
        "initSale": {
            "auctionPeriod": 1209600,
            "delay": 3600,
            "miniAuctionPeriod": 21600,
            "periodMaxDiscount": 800000000000000000,
            "periodStartingPremium": 1200000000000000000,
            "reserveAutomationContracts": [
                "RESERVE_AUTOMATION_WBTC",
                "RESERVE_AUTOMATION_cbETH",
                "RESERVE_AUTOMATION_rETH"
            ]
        },
        "setMRDSpeeds": [
            {
                "emissionToken": "xWELL_PROXY",
                "market": "MOONWELL_USDC",
                "newBorrowSpeed": -1,
                "newEndTime": 1760103018,
                "newSupplySpeed": 81088749185872770
            },
            {
                "emissionToken": "xWELL_PROXY",
                "market": "MOONWELL_USDT",
                "newBorrowSpeed": -1,
                "newEndTime": 1760103018,
                "newSupplySpeed": 2965980871227120
            },
            {
                "emissionToken": "xWELL_PROXY",
                "market": "MOONWELL_DAI",
                "newBorrowSpeed": -1,
                "newEndTime": 1760103018,
                "newSupplySpeed": 2444102891061245
            },
            {
                "emissionToken": "xWELL_PROXY",
                "market": "MOONWELL_WBTC",
                "newBorrowSpeed": -1,
                "newEndTime": 1760103018,
                "newSupplySpeed": -1
            },
            {
                "emissionToken": "xWELL_PROXY",
                "market": "MOONWELL_WETH",
                "newBorrowSpeed": -1,
                "newEndTime": 1760103018,
                "newSupplySpeed": 217123293922030980
            },
            {
                "emissionToken": "xWELL_PROXY",
                "market": "MOONWELL_wstETH",
                "newBorrowSpeed": -1,
                "newEndTime": 1760103018,
                "newSupplySpeed": 42252538635455820
            },
            {
                "emissionToken": "xWELL_PROXY",
                "market": "MOONWELL_cbETH",
                "newBorrowSpeed": -1,
                "newEndTime": 1760103018,
                "newSupplySpeed": -1
            },
            {
                "emissionToken": "xWELL_PROXY",
                "market": "MOONWELL_rETH",
                "newBorrowSpeed": -1,
                "newEndTime": 1760103018,
                "newSupplySpeed": 6171169760547641
            },
            {
                "emissionToken": "xWELL_PROXY",
                "market": "MOONWELL_OP",
                "newBorrowSpeed": -1,
                "newEndTime": 1760103018,
                "newSupplySpeed": 21718420273245580
            },
            {
                "emissionToken": "xWELL_PROXY",
                "market": "MOONWELL_weETH",
                "newBorrowSpeed": -1,
                "newEndTime": 1760103018,
                "newSupplySpeed": 73548423715544460
            },
            {
                "emissionToken": "xWELL_PROXY",
                "market": "MOONWELL_VELO",
                "newBorrowSpeed": -1,
                "newEndTime": 1760103018,
                "newSupplySpeed": 37432820894710640
            },
            {
                "emissionToken": "xWELL_PROXY",
                "market": "MOONWELL_wrsETH",
                "newBorrowSpeed": -1,
                "newEndTime": 1760103018,
                "newSupplySpeed": 1367879387390560
            },
            {
                "emissionToken": "xWELL_PROXY",
                "market": "MOONWELL_USDT0",
                "newBorrowSpeed": -1,
                "newEndTime": 1760103018,
                "newSupplySpeed": 4384130393386430
            }
        ],
        "stkWellEmissionsPerSecond": 29578241543723750,
        "transferFrom": [
            {
                "amount": 1.1866115660238008e24,
                "from": "TEMPORAL_GOVERNOR",
                "to": "MRD_PROXY",
                "token": "xWELL_PROXY"
            },
            {
                "amount": 6.8045669942576546e22,
                "from": "TEMPORAL_GOVERNOR",
                "to": "ECOSYSTEM_RESERVE_PROXY",
                "token": "xWELL_PROXY"
            }
        ],
        "transferReserves": [
            {
                "amount": 538,
                "market": "MOONWELL_WBTC",
                "to": "RESERVE_AUTOMATION_WBTC"
            },
            {
                "amount": 34083760676,
                "market": "MOONWELL_cbETH",
                "to": "RESERVE_AUTOMATION_cbETH"
            },
            {
                "amount": 215630451615000,
                "market": "MOONWELL_rETH",
                "to": "RESERVE_AUTOMATION_rETH"
            }
        ],
        "withdrawWell": [
            {
                "amount": 1.754999999999976e21,
                "to": "ECOSYSTEM_RESERVE_PROXY"
            }
        ],
        "multiRewarder": [
            {
                "distributor": "TEMPORAL_GOVERNOR",
                "duration": 2419200,
                "reward": 6.980067994257652e22,
                "rewardToken": "xWELL_PROXY",
                "vault": "USDC_MULTI_REWARDER"
            }
        ],
        "merkleCampaigns": []
    },
    "1284": {
        "bridgeToRecipient": [
            {
                "amount": 2.31727583564751e25,
                "nativeValue": 13826574196697262000,
                "network": 8453,
                "target": "TEMPORAL_GOVERNOR"
            },
            {
                "amount": 1.326212947908954e24,
                "nativeValue": 13826574196697262000,
                "network": 10,
                "target": "TEMPORAL_GOVERNOR"
            },
            {
                "amount": 6.980069094257652e22,
                "nativeValue": 13826574196697262000,
                "network": 10,
                "target": "DEX_RELAYER"
            }
        ],
        "transferFrom": [
            {
                "amount": 1.1503721242871822e25,
                "from": "MGLIMMER_MULTISIG",
                "to": "MULTICHAIN_GOVERNOR_PROXY",
                "token": "GOVTOKEN"
            },
            {
                "amount": 1.166903720360328e25,
                "from": "F-GLMR-DEVGRANT",
                "to": "MULTICHAIN_GOVERNOR_PROXY",
                "token": "GOVTOKEN"
            },
            {
                "amount": 1.3960137188515303e24,
                "from": "MGLIMMER_MULTISIG",
                "to": "MULTICHAIN_GOVERNOR_PROXY",
                "token": "GOVTOKEN"
            },
            {
                "amount": 15160487476317736790718,
                "from": "MGLIMMER_MULTISIG",
                "to": "MULTICHAIN_GOVERNOR_PROXY",
                "token": "GOVTOKEN"
            },
            {
                "amount": 1.1506207234924617e23,
                "from": "MGLIMMER_MULTISIG",
                "to": "UNITROLLER",
                "token": "GOVTOKEN"
            },
            {
                "amount": 1.126649458419702e23,
                "from": "MGLIMMER_MULTISIG",
                "to": "ECOSYSTEM_RESERVE_PROXY",
                "token": "GOVTOKEN"
            }
        ],
        "addRewardInfo": {
            "amount": 15160487476317736790718,
            "endTimestamp": 1760103018,
            "pid": 15,
            "rewardPerSec": 4954378528596151,
            "target": "STELLASWAP_REWARDER"
        },
        "setRewardSpeed": [
            {
                "market": "mGLIMMER",
                "newBorrowSpeed": 1948434893351892,
                "newSupplySpeed": 1948434893351892,
                "rewardType": 0
            },
            {
                "market": "mGLIMMER",
                "newBorrowSpeed": 3175082240780388,
                "newSupplySpeed": 3175082240780388,
                "rewardType": 1
            },
            {
                "market": "mxcDOT",
                "newBorrowSpeed": 1,
                "newSupplySpeed": 41676422948569170,
                "rewardType": 0
            },
            {
                "market": "mxcDOT",
                "newBorrowSpeed": 1,
                "newSupplySpeed": 67914032341934580,
                "rewardType": 1
            },
            {
                "market": "mFRAX",
                "newBorrowSpeed": 120138752015167,
                "newSupplySpeed": 120138752015167,
                "rewardType": 0
            },
            {
                "market": "mFRAX",
                "newBorrowSpeed": 195772729822482,
                "newSupplySpeed": 195772729822482,
                "rewardType": 1
            },
            {
                "market": "mETHwh",
                "newBorrowSpeed": 1,
                "newSupplySpeed": 0,
                "rewardType": 0
            },
            {
                "market": "mETHwh",
                "newBorrowSpeed": 1,
                "newSupplySpeed": 0,
                "rewardType": 1
            },
            {
                "market": "MOONWELL_mWBTC",
                "newBorrowSpeed": 1,
                "newSupplySpeed": 0,
                "rewardType": 0
            },
            {
                "market": "MOONWELL_mWBTC",
                "newBorrowSpeed": 1,
                "newSupplySpeed": 0,
                "rewardType": 1
            },
            {
                "market": "mUSDCwh",
                "newBorrowSpeed": 174359163429029,
                "newSupplySpeed": 174359163429029,
                "rewardType": 0
            },
            {
                "market": "mUSDCwh",
                "newBorrowSpeed": 284127883979983,
                "newSupplySpeed": 284127883979983,
                "rewardType": 1
            },
            {
                "market": "mxcUSDT",
                "newBorrowSpeed": 329969853501648,
                "newSupplySpeed": 329969853501648,
                "rewardType": 0
            },
            {
                "market": "mxcUSDT",
                "newBorrowSpeed": 537704095436139,
                "newSupplySpeed": 537704095436139,
                "rewardType": 1
            },
            {
                "market": "mxcUSDC",
                "newBorrowSpeed": 369902800679206,
                "newSupplySpeed": 369902800679206,
                "rewardType": 0
            },
            {
                "market": "mxcUSDC",
                "newBorrowSpeed": 602777037743884,
                "newSupplySpeed": 602777037743884,
                "rewardType": 1
            }
        ],
        "stkWellEmissionsPerSecond": 46571158168803816,
        "withdrawWell": []
    },
    "8453": {
        "initSale": {
            "auctionPeriod": 1209600,
            "delay": 3600,
            "miniAuctionPeriod": 21600,
            "periodMaxDiscount": 800000000000000000,
            "periodStartingPremium": 1200000000000000000,
            "reserveAutomationContracts": [
                "RESERVE_AUTOMATION_USDBC",
                "RESERVE_AUTOMATION_cbETH",
                "RESERVE_AUTOMATION_DAI",
                "RESERVE_AUTOMATION_USDC",
                "RESERVE_AUTOMATION_wstETH",
                "RESERVE_AUTOMATION_AERO",
                "RESERVE_AUTOMATION_weETH",
                "RESERVE_AUTOMATION_VIRTUAL"
            ]
        },
        "multiRewarder": [],
        "setMRDSpeeds": [
            {
                "emissionToken": "xWELL_PROXY",
                "market": "MOONWELL_USDBC",
                "newBorrowSpeed": -1,
                "newEndTime": 1760103018,
                "newSupplySpeed": -1
            },
            {
                "emissionToken": "USDC",
                "market": "MOONWELL_USDBC",
                "newBorrowSpeed": -1,
                "newEndTime": -1,
                "newSupplySpeed": -1
            },
            {
                "emissionToken": "xWELL_PROXY",
                "market": "MOONWELL_WETH",
                "newBorrowSpeed": 381542555167328100,
                "newEndTime": 1760103018,
                "newSupplySpeed": 381542555167328100
            },
            {
                "emissionToken": "USDC",
                "market": "MOONWELL_WETH",
                "newBorrowSpeed": -1,
                "newEndTime": -1,
                "newSupplySpeed": -1
            },
            {
                "emissionToken": "xWELL_PROXY",
                "market": "MOONWELL_cbETH",
                "newBorrowSpeed": -1,
                "newEndTime": 1760103018,
                "newSupplySpeed": -1
            },
            {
                "emissionToken": "USDC",
                "market": "MOONWELL_cbETH",
                "newBorrowSpeed": -1,
                "newEndTime": -1,
                "newSupplySpeed": -1
            },
            {
                "emissionToken": "xWELL_PROXY",
                "market": "MOONWELL_DAI",
                "newBorrowSpeed": -1,
                "newEndTime": 1760103018,
                "newSupplySpeed": -1
            },
            {
                "emissionToken": "USDC",
                "market": "MOONWELL_DAI",
                "newBorrowSpeed": -1,
                "newEndTime": -1,
                "newSupplySpeed": -1
            },
            {
                "emissionToken": "xWELL_PROXY",
                "market": "MOONWELL_USDC",
                "newBorrowSpeed": -1,
                "newEndTime": 1760103018,
                "newSupplySpeed": 1358471708625441500
            },
            {
                "emissionToken": "USDC",
                "market": "MOONWELL_USDC",
                "newBorrowSpeed": -1,
                "newEndTime": -1,
                "newSupplySpeed": -1
            },
            {
                "emissionToken": "xWELL_PROXY",
                "market": "MOONWELL_wstETH",
                "newBorrowSpeed": -1,
                "newEndTime": 1760103018,
                "newSupplySpeed": -1
            },
            {
                "emissionToken": "USDC",
                "market": "MOONWELL_wstETH",
                "newBorrowSpeed": -1,
                "newEndTime": -1,
                "newSupplySpeed": -1
            },
            {
                "emissionToken": "xWELL_PROXY",
                "market": "MOONWELL_rETH",
                "newBorrowSpeed": -1,
                "newEndTime": 1760103018,
                "newSupplySpeed": -1
            },
            {
                "emissionToken": "USDC",
                "market": "MOONWELL_rETH",
                "newBorrowSpeed": -1,
                "newEndTime": -1,
                "newSupplySpeed": -1
            },
            {
                "emissionToken": "xWELL_PROXY",
                "market": "MOONWELL_AERO",
                "newBorrowSpeed": 152508841186989630,
                "newEndTime": 1760103018,
                "newSupplySpeed": 124779960971173310
            },
            {
                "emissionToken": "USDC",
                "market": "MOONWELL_AERO",
                "newBorrowSpeed": -1,
                "newEndTime": -1,
                "newSupplySpeed": -1
            },
            {
                "emissionToken": "xWELL_PROXY",
                "market": "MOONWELL_weETH",
                "newBorrowSpeed": -1,
                "newEndTime": 1760103018,
                "newSupplySpeed": -1
            },
            {
                "emissionToken": "USDC",
                "market": "MOONWELL_weETH",
                "newBorrowSpeed": -1,
                "newEndTime": -1,
                "newSupplySpeed": -1
            },
            {
                "emissionToken": "xWELL_PROXY",
                "market": "MOONWELL_cbBTC",
                "newBorrowSpeed": 197176101512127100,
                "newEndTime": 1760103018,
                "newSupplySpeed": 197176101512127100
            },
            {
                "emissionToken": "USDC",
                "market": "MOONWELL_cbBTC",
                "newBorrowSpeed": -1,
                "newEndTime": -1,
                "newSupplySpeed": -1
            },
            {
                "emissionToken": "xWELL_PROXY",
                "market": "MOONWELL_EURC",
                "newBorrowSpeed": 16803751006495270,
                "newEndTime": 1760103018,
                "newSupplySpeed": 16803751006495270
            },
            {
                "emissionToken": "USDC",
                "market": "MOONWELL_EURC",
                "newBorrowSpeed": -1,
                "newEndTime": -1,
                "newSupplySpeed": -1
            },
            {
                "emissionToken": "xWELL_PROXY",
                "market": "MOONWELL_wrsETH",
                "newBorrowSpeed": -1,
                "newEndTime": 1760103018,
                "newSupplySpeed": -1
            },
            {
                "emissionToken": "USDC",
                "market": "MOONWELL_wrsETH",
                "newBorrowSpeed": -1,
                "newEndTime": -1,
                "newSupplySpeed": -1
            },
            {
                "emissionToken": "xWELL_PROXY",
                "market": "MOONWELL_WELL",
                "newBorrowSpeed": 44295481201266690,
                "newEndTime": 1760103018,
                "newSupplySpeed": 36241757346490930
            },
            {
                "emissionToken": "USDC",
                "market": "MOONWELL_WELL",
                "newBorrowSpeed": -1,
                "newEndTime": -1,
                "newSupplySpeed": -1
            },
            {
                "emissionToken": "xWELL_PROXY",
                "market": "MOONWELL_USDS",
                "newBorrowSpeed": -1,
                "newEndTime": 1760103018,
                "newSupplySpeed": -1
            },
            {
                "emissionToken": "USDC",
                "market": "MOONWELL_USDS",
                "newBorrowSpeed": -1,
                "newEndTime": -1,
                "newSupplySpeed": -1
            },
            {
                "emissionToken": "xWELL_PROXY",
                "market": "MOONWELL_TBTC",
                "newBorrowSpeed": 6068675668517214,
                "newEndTime": 1760103018,
                "newSupplySpeed": 6068675668517214
            },
            {
                "emissionToken": "USDC",
                "market": "MOONWELL_TBTC",
                "newBorrowSpeed": -1,
                "newEndTime": -1,
                "newSupplySpeed": -1
            },
            {
                "emissionToken": "xWELL_PROXY",
                "market": "MOONWELL_LBTC",
                "newBorrowSpeed": 24780575628471230,
                "newEndTime": 1760103018,
                "newSupplySpeed": 24780575628471230
            },
            {
                "emissionToken": "USDC",
                "market": "MOONWELL_LBTC",
                "newBorrowSpeed": -1,
                "newEndTime": -1,
                "newSupplySpeed": -1
            },
            {
                "emissionToken": "xWELL_PROXY",
                "market": "MOONWELL_VIRTUAL",
                "newBorrowSpeed": 39885106966252580,
                "newEndTime": 1760103018,
                "newSupplySpeed": 32633269336024830
            },
            {
                "emissionToken": "USDC",
                "market": "MOONWELL_VIRTUAL",
                "newBorrowSpeed": -1,
                "newEndTime": -1,
                "newSupplySpeed": -1
            },
            {
                "emissionToken": "xWELL_PROXY",
                "market": "MOONWELL_MORPHO",
                "newBorrowSpeed": 91002014225072300,
                "newEndTime": 1760103018,
                "newSupplySpeed": 74456193456877330
            },
            {
                "emissionToken": "USDC",
                "market": "MOONWELL_MORPHO",
                "newBorrowSpeed": -1,
                "newEndTime": -1,
                "newSupplySpeed": -1
            },
            {
                "emissionToken": "xWELL_PROXY",
                "market": "MOONWELL_cbXRP",
                "newBorrowSpeed": 66882950527687750,
                "newEndTime": 1760103018,
                "newSupplySpeed": 54722414068108160
            },
            {
                "emissionToken": "USDC",
                "market": "MOONWELL_cbXRP",
                "newBorrowSpeed": -1,
                "newEndTime": -1,
                "newSupplySpeed": -1
            }
        ],
        "transferFrom": [
            {
                "amount": 8.052604790010274e24,
                "from": "TEMPORAL_GOVERNOR",
                "to": "MRD_PROXY",
                "token": "xWELL_PROXY"
            },
            {
                "amount": 6.0019192879185e23,
                "from": "F-AERO_MULTISIG",
                "to": "DEX_RELAYER",
                "token": "xWELL_PROXY"
            }
        ],
        "transferReserves": [
            {
                "amount": 1574129,
                "market": "MOONWELL_USDBC",
                "to": "RESERVE_AUTOMATION_USDBC"
            },
            {
                "amount": 729320241156243000,
                "market": "MOONWELL_cbETH",
                "to": "RESERVE_AUTOMATION_cbETH"
            },
            {
                "amount": 63673330928504800000,
                "market": "MOONWELL_DAI",
                "to": "RESERVE_AUTOMATION_DAI"
            },
            {
                "amount": 50136740061,
                "market": "MOONWELL_USDC",
                "to": "RESERVE_AUTOMATION_USDC"
            },
            {
                "amount": 387515092877987000,
                "market": "MOONWELL_wstETH",
                "to": "RESERVE_AUTOMATION_wstETH"
            },
            {
                "amount": 2.216886241275058e22,
                "market": "MOONWELL_AERO",
                "to": "RESERVE_AUTOMATION_AERO"
            },
            {
                "amount": 1719944075693354000,
                "market": "MOONWELL_weETH",
                "to": "RESERVE_AUTOMATION_weETH"
            },
            {
                "amount": 1.910305461889973e21,
                "market": "MOONWELL_VIRTUAL",
                "to": "RESERVE_AUTOMATION_VIRTUAL"
            }
        ],
        "withdrawWell": [
            {
                "amount": 172000000000218860000,
                "to": "TEMPORAL_GOVERNOR"
            }
        ],
        "merkleCampaigns": [
            {
                "amount": 1.5120325547464826e25,
                "duration": 4838400,
                "rewardToken": "xWELL_PROXY",
                "startTimestamp": 1755264618
            }
        ]
    },
    "endTimeSTamp": 1760103018,
    "startTimeStamp": 1757683818
}
